{
  "collectionName": "components_elements_features_carousel_items",
  "info": {
    "displayName": "Features Carousel Item",
    "icon": "stop",
    "description": ""
  },
  "options": {},
  "attributes": {
    "title": {
      "type": "string"
    },
    "description": {
      "type": "richtext"
    },
    "image": {
      "type": "media",
      "multiple": false,
      "required": false,
      "allowedTypes": [
        "images",
        "files",
        "videos",
        "audios"
      ]
    },
    "cardBgColor": {
      "type": "customField",
      "customField": "plugin::color-picker.color"
    }
  }
}
